dataenv/__init__.py
dataenv/core.py
dataenv-0.1.dist-info/licenses/LICENSE
dataenv-0.1.dist-info/METADATA
dataenv-0.1.dist-info/WHEEL
dataenv-0.1.dist-info/top_level.txt
dataenv-0.1.dist-info/RECORD
