Metadata-Version: 2.4
Name: DataEnv
Version: 0.1
Summary: The package for doing many sorts of operations with data.
Home-page: https://github.com/ProgVM/DataEnv/
Author: ProgVM
Author-email: progvminc@gmail.com
License: Apache License 2.0
Classifier: Programming Language :: Python :: 3
Classifier: License :: OSI Approved :: Apache Software License
Classifier: Operating System :: OS Independent
Requires-Python: >=3.6
License-File: LICENSE
Dynamic: author
Dynamic: author-email
Dynamic: classifier
Dynamic: description
Dynamic: description-content-type
Dynamic: home-page
Dynamic: license
Dynamic: license-file
Dynamic: requires-python
Dynamic: summary
